TextFeatureSelection.py
TextFeatureSelection-0.3.0.dist-info/LICENSE
TextFeatureSelection-0.3.0.dist-info/METADATA
TextFeatureSelection-0.3.0.dist-info/WHEEL
TextFeatureSelection-0.3.0.dist-info/top_level.txt
TextFeatureSelection-0.3.0.dist-info/RECORD
