Metadata-Version: 2.1
Name: TextFeatureSelection
Version: 0.3.0
Summary: Python library for feature selection for text features. It has filter method, genetic algorithm and TextFeatureSelectionEnsemble for improving text classification models. Helps improve your machine learning models
Home-page: https://github.com/StatguyUser/TextFeatureSelection
Author: StatguyUser
License: UNKNOWN
Download-URL: https://github.com/StatguyUser/TextFeatureSelection.git
Platform: UNKNOWN
Requires-Dist: numpy
Requires-Dist: pandas
Requires-Dist: scikit-learn
Requires-Dist: xgboost
Requires-Dist: nltk
Requires-Dist: MetaHeuristicsFS
